fairmaterials/__init__.py
fairmaterials/__main__.py
fairmaterials/fair_sheet_parser.py
fairmaterials/rdflib_graph_merger.py
fairmaterials/rdflib_graph_saver.py
fairmaterials-0.4.3.dist-info/LICENSE
fairmaterials-0.4.3.dist-info/METADATA
fairmaterials-0.4.3.dist-info/WHEEL
fairmaterials-0.4.3.dist-info/RECORD
