Metadata-Version: 2.1
Name: FAIRmaterials
Version: 0.4.3
Summary: Translates several CSV files with ontological terms and corresponding data into RDF triples. These RDF triples are stored in OWL and JSON-LD files, facilitating data accessibility, interoperability, and knowledge unification. The triples are also visualized in a graph saved as an SVG. The input CSVs must be formatted with a template from a public Google Sheet; see README or vignette for more information. This is a tool is used by the SDLE Research Center at Case Western Reserve Universi
License: BSD-2-Clause
Author: Alexander Harding Bradley
Requires-Python: >=3.9.18,<4.0.0
Classifier: License :: OSI Approved :: BSD License
Classifier: Programming Language :: Python :: 3
Classifier: Programming Language :: Python :: 3.10
Classifier: Programming Language :: Python :: 3.11
Classifier: Programming Language :: Python :: 3.12
Requires-Dist: graphviz (>=0.20.1,<0.21.0)
Requires-Dist: matplotlib (>=3.6.2,<4.0.0)
Requires-Dist: numpy (>=1.23.5,<2.0.0)
Requires-Dist: pylode (>=3.1.4,<4.0.0)
Requires-Dist: rdflib (>=7.0.0,<8.0.0)
